PythonJiqiXuexi/README.md
PythonJiqiXuexi/__init__.py
PythonJiqiXuexi/__main__.py
PythonJiqiXuexi/file.epub
PythonJiqiXuexi/index.html
PythonJiqiXuexi/css/__init__.py
PythonJiqiXuexi/css/annotations.css
PythonJiqiXuexi/css/main.css
PythonJiqiXuexi/css/normalize.css
PythonJiqiXuexi/css/popup.css
PythonJiqiXuexi/font/__init__.py
PythonJiqiXuexi/font/fontello.eot
PythonJiqiXuexi/font/fontello.svg
PythonJiqiXuexi/font/fontello.ttf
PythonJiqiXuexi/font/fontello.woff
PythonJiqiXuexi/img/__init__.py
PythonJiqiXuexi/img/annotator-glyph-sprite.png
PythonJiqiXuexi/img/annotator-icon-sprite.png
PythonJiqiXuexi/img/apple-touch-icon.png
PythonJiqiXuexi/img/cancelfullscreen.png
PythonJiqiXuexi/img/close.png
PythonJiqiXuexi/img/fullscreen.png
PythonJiqiXuexi/img/loader.gif
PythonJiqiXuexi/img/menu-icon.png
PythonJiqiXuexi/img/save.png
PythonJiqiXuexi/img/saved.png
PythonJiqiXuexi/img/settings-s.png
PythonJiqiXuexi/img/settings.png
PythonJiqiXuexi/img/star.png
PythonJiqiXuexi/js/__init__.py
PythonJiqiXuexi/js/epub.js
PythonJiqiXuexi/js/epub.min.js
PythonJiqiXuexi/js/epub.min.map
PythonJiqiXuexi/js/hooks.min.js
PythonJiqiXuexi/js/hooks.min.map
PythonJiqiXuexi/js/reader.js
PythonJiqiXuexi/js/reader.js.map
PythonJiqiXuexi/js/reader.min.js
PythonJiqiXuexi/js/reader.min.map
PythonJiqiXuexi/js/hooks/__init__.py
PythonJiqiXuexi/js/hooks/extensions/__init__.py
PythonJiqiXuexi/js/hooks/extensions/highlight.js
PythonJiqiXuexi/js/libs/__init__.py
PythonJiqiXuexi/js/libs/jquery.min.js
PythonJiqiXuexi/js/libs/localforage.min.js
PythonJiqiXuexi/js/libs/screenfull.js
PythonJiqiXuexi/js/libs/screenfull.min.js
PythonJiqiXuexi/js/libs/zip.min.js
PythonJiqiXuexi/js/plugins/__init__.py
PythonJiqiXuexi/js/plugins/hypothesis.js
PythonJiqiXuexi/js/plugins/search.js
python_jiqi_xuexi-2024.3.2.0.dist-info/METADATA
python_jiqi_xuexi-2024.3.2.0.dist-info/WHEEL
python_jiqi_xuexi-2024.3.2.0.dist-info/entry_points.txt
python_jiqi_xuexi-2024.3.2.0.dist-info/top_level.txt
python_jiqi_xuexi-2024.3.2.0.dist-info/RECORD
